CHANGES
LICENSE
MANIFEST.in
Makefile
README
runtests.py
select_backportmodule.c
select_backportmodule.h
setup.cfg
setup.py
select_backport.egg-info/PKG-INFO
select_backport.egg-info/SOURCES.txt
select_backport.egg-info/dependency_links.txt
select_backport.egg-info/top_level.txt
tests/__init__.py
tests/test_epoll.py
tests/test_kqueue.py
tests/test_select_backport.py