Metadata-Version: 1.1
Name: select-backport
Version: 0.2
Summary: Backport of the new select module with epoll and kqueue interface
Home-page: UNKNOWN
Author: Gora Khargosh
Author-email: gora.khargosh@gmail.com
License: MIT
Download-URL: http://pypi.python.org/
Keywords: select poll epoll kqueue
Platform: Linux 2.6
Platform: BSD
Platform: Mac OS X
Classifier: Development Status :: 3 - Alpha
Classifier: Intended Audience :: Developers
Classifier: License :: OSI Approved :: MIT License
Classifier: Natural Language :: English
Classifier: Programming Language :: C
Classifier: Programming Language :: Python
Classifier: Operating System :: MacOS :: MacOS X
Classifier: Operating System :: POSIX :: BSD
Classifier: Operating System :: POSIX :: Linux
Classifier: Topic :: System :: Networking
Provides: select_backport
